{"version": 0.6, "generator": "Overpass API 0.7.62.1 084b4234", "osm3s": {"timestamp_osm_base": "2024-09-14T19:42:13Z", "copyright": "The data included in this document is from www.openstreetmap.org. The data is made available under ODbL."}, "elements": [{"type": "node", "id": 1825166757, "lat": 28.7019591, "lon": 77.1057097}, {"type": "node", "id": 1825166830, "lat": 28.7025881, "lon": 77.1062607}, {"type": "node", "id": 1825166831, "lat": 28.7026015, "lon": 77.1062762}, {"type": "node", "id": 1825166843, "lat": 28.7028258, "lon": 77.1044238}, {"type": "node", "id": 1825166863, "lat": 28.7031901, "lon": 77.1068024}, {"type": "node", "id": 1825166865, "lat": 28.7032083, "lon": 77.1068276}, {"type": "node", "id": 1825166881, "lat": 28.7034548, "lon": 77.1049748}, {"type": "node", "id": 1825166882, "lat": 28.7034762, "lon": 77.1050045}, {"type": "node", "id": 1825166921, "lat": 28.7040647, "lon": 77.1055306}, {"type": "node", "id": 1825167045, "lat": 28.7040787, "lon": 77.1055452}, {"type": "node", "id": 1825167060, "lat": 28.7042387, "lon": 77.1077366}, {"type": "node", "id": 1825167117, "lat": 28.705109, "lon": 77.1064541}, {"type": "node", "id": 3914548790, "lat": 28.7041742, "lon": 77.103015}, {"type": "node", "id": 3914548791, "lat": 28.7039217, "lon": 77.102806}, {"type": "node", "id": 3914548792, "lat": 28.7040251, "lon": 77.1026436}, {"type": "node", "id": 3914548793, "lat": 28.7042776, "lon": 77.1028527}, {"type": "way", "id": 171496276, "nodes": [1825166881, 1825166830, 1825166757, 1825166843, 1825166881], "tags": {"amenity": "school"}}, {"type": "way", "id": 171496282, "nodes": [1825166882, 1825166921, 1825166863, 1825166831, 1825166882], "tags": {"amenity": "school"}}, {"type": "way", "id": 171496283, "nodes": [1825167045, 1825167117, 1825167060, 1825166865, 1825167045], "tags": {"amenity": "school"}}, {"type": "way", "id": 388242027, "nodes": [3914548790, 3914548791, 3914548792, 3914548793, 3914548790], "tags": {"amenity": "school", "building": "commercial", "name": "Kendriya Vidyalaya"}}]}